omopsurvey/__init__.py
omopsurvey/codebooks.py
omopsurvey/pivot_data.py
omopsurvey/recode_missing.py
omopsurvey/response_set.py
omopsurvey/survey_key.csv
omopsurvey/tests/codebook_test.py
omopsurvey/tests/map_responses_test.py
omopsurvey/tests/pivot_data_test.py
omopsurvey/tests/recode_missing_test.py
omopsurvey/vignettes/example_basics.ipynb
omopsurvey/vignettes/example_healthcare.ipynb
omopsurvey/vignettes/example_sdoh.ipynb
omopsurvey-0.0.8.dist-info/METADATA
omopsurvey-0.0.8.dist-info/WHEEL
omopsurvey-0.0.8.dist-info/RECORD
